pm/__init__.py
pm/core/__init__.py
pm/core/errors.py
pm/core/http.py
pm/core/retry.py
pm/core/utils.py
pm/polymarket/__init__.py
pm/polymarket/client.py
pm/polymarket/config.py
pm/polymarket/constants.py
pm/polymarket/event.py
pm/polymarket/market.py
pm/polymarket/api/__init__.py
pm/polymarket/api/handlers/__init__.py
pm/polymarket/api/handlers/clob_handler.py
pm/polymarket/api/handlers/data_handler.py
pm/polymarket/api/handlers/gamma_handler.py
pm/polymarket/api/sources/__init__.py
pm/polymarket/api/sources/clob_source.py
pm/polymarket/api/sources/data_source.py
pm/polymarket/api/sources/gamma_source.py
lattica_pm-0.1.0.dist-info/METADATA
lattica_pm-0.1.0.dist-info/WHEEL
lattica_pm-0.1.0.dist-info/licenses/LICENSE.md
lattica_pm-0.1.0.dist-info/RECORD
