Metadata-Version: 2.4
Name: lattica-pm
Version: 0.1.0
Summary: Prediction market data aggregator
Author-email: wkflanders <wflan@seas.upenn.edu>
License-Expression: MIT
License-File: LICENSE.md
Classifier: Programming Language :: Python :: 3 :: Only
Classifier: Programming Language :: Python :: 3.11
Classifier: Programming Language :: Python :: 3.12
Classifier: Programming Language :: Python :: 3.13
Classifier: Programming Language :: Python :: 3.14
Requires-Python: >=3.11
Requires-Dist: httpx>=0.27
Requires-Dist: pandas>=2
